ampel/catalogmatch/.gitignore
ampel/conf/ampel-catalogmatch/ampel.yml
ampel/ztf/base/CatalogMatchFilter.py
ampel/ztf/base/CatalogMatchUnit.py
ampel/ztf/t2/T2CatalogMatch.py
ampel/ztf/t3/complement/TNSNames.py
ampel/ztf/t3/complement/TNSReports.py
ampel_catalogmatch-0.10.0a3.dist-info/METADATA
ampel_catalogmatch-0.10.0a3.dist-info/WHEEL
ampel_catalogmatch-0.10.0a3.dist-info/RECORD
