Metadata-Version: 2.4
Name: ampel-catalogmatch
Version: 0.10.0a3
Summary: Astronomical catalog matching for Ampel
License-Expression: BSD-3-Clause
Author: Jakob van Santen
Author-email: jakob.van.santen@desy.de
Maintainer: Jakob van Santen
Maintainer-email: jakob.van.santen@desy.de
Requires-Python: >=3.11, <4
Classifier: Development Status :: 3 - Alpha
Classifier: Intended Audience :: Science/Research
Classifier: Programming Language :: Python :: 3.11
Classifier: Programming Language :: Python :: 3.12
Classifier: Programming Language :: Python :: 3.13
Classifier: Programming Language :: Python :: 3.14
Classifier: Topic :: Scientific/Engineering :: Information Analysis
Classifier: Topic :: Scientific/Engineering :: Astronomy
Classifier: Typing :: Typed
Requires-Dist: ampel-alerts (>=0.10.3,<0.11.0)
Requires-Dist: ampel-interface (>=0.10.4.post2,<0.11)
Requires-Dist: requests (>=2.32.5,<3.0.0)
Requires-Dist: requests-toolbelt (>=1.0.0,<2.0.0)
Requires-Dist: tenacity (>=9.1.2,<10.0.0)
Project-URL: Homepage, https://ampelproject.github.io
Project-URL: Repository, https://github.com/AmpelAstro/Ampel-CatalogMatch
